wristpy/__init__.py
wristpy/__main__.py
wristpy/core/__init__.py
wristpy/core/cli.py
wristpy/core/computations.py
wristpy/core/config.py
wristpy/core/exceptions.py
wristpy/core/models.py
wristpy/core/orchestrator.py
wristpy/io/__init__.py
wristpy/io/readers/__init__.py
wristpy/io/readers/readers.py
wristpy/io/writers/__init__.py
wristpy/io/writers/writers.py
wristpy/processing/__init__.py
wristpy/processing/_nimbaldetach.py
wristpy/processing/analytics.py
wristpy/processing/calibration.py
wristpy/processing/idle_sleep_mode_imputation.py
wristpy/processing/metrics.py
wristpy/processing/mims.py
wristpy/processing/processing_utils.py
wristpy-0.2.2.dist-info/METADATA
wristpy-0.2.2.dist-info/WHEEL
wristpy-0.2.2.dist-info/entry_points.txt
wristpy-0.2.2.dist-info/licenses/LICENSE
wristpy-0.2.2.dist-info/RECORD
