Metadata-Version: 2.4
Name: wristpy
Version: 0.2.2
Summary: wristpy is a Python package designed for processing and analyzing wrist-worn accelerometer data.
License: LGPL-2.1
License-File: LICENSE
Author: Adam Santorelli
Author-email: adam.santorelli@childmind.org
Requires-Python: >=3.10,<3.14
Classifier: License :: OSI Approved
Classifier: Programming Language :: Python :: 3
Classifier: Programming Language :: Python :: 3.10
Classifier: Programming Language :: Python :: 3.11
Classifier: Programming Language :: Python :: 3.12
Classifier: Programming Language :: Python :: 3.13
Requires-Dist: actfast (>=1.1.3,<2.0.0)
Requires-Dist: numpy (>=2.1.0,<3.0.0)
Requires-Dist: polars (>=1.21.0,<2.0.0)
Requires-Dist: pyarrow (>=18,<20)
Requires-Dist: pydantic (>=2.11.1,<3.0.0)
Requires-Dist: pydantic-settings (>=2.3.4,<3.0.0)
Requires-Dist: rich (>=14.1.0,<15.0.0)
Requires-Dist: scikit-learn (>=1.7.1,<2.0.0)
Requires-Dist: scipy (>=1.14.1,<2.0.0)
Requires-Dist: typer (>=0.15.2,<0.16.0)
